[{"name":"start_processing.action_controller","payload":{"controller":"PaymentsController","action":"index","params":{"action":"index","controller":"payments"},"format":"html","method":"GET","path":"/payments"},"time":"2013-02-25T15:27:25+02:00","transaction_id":"1dd8cd49dbc9a7e308f3","end":"2013-02-25T15:27:25+02:00","duration":0.00482},{"name":"sql.active_record","payload":{"sql":"SHOW FULL FIELDS FROM `payments`","name":"SCHEMA","connection_id":93140860,"binds":[]},"time":"2013-02-25T15:27:25+02:00","transaction_id":"aa656234c5e4dcb884c3","end":"2013-02-25T15:27:25+02:00","duration":0.7757280000000001},{"name":"sql.active_record","payload":{"sql":"SELECT `payments`.* FROM `payments` ","name":"Payment Load","connection_id":93140860,"binds":[]},"time":"2013-02-25T15:27:25+02:00","transaction_id":"aa656234c5e4dcb884c3","end":"2013-02-25T15:27:25+02:00","duration":36.371105},{"name":"sql.active_record","payload":{"sql":"SHOW FULL FIELDS FROM `manuals`","name":"SCHEMA","connection_id":93140860,"binds":[]},"time":"2013-02-25T15:27:25+02:00","transaction_id":"aa656234c5e4dcb884c3","end":"2013-02-25T15:27:25+02:00","duration":0.842077},{"name":"sql.active_record","payload":{"sql":"SELECT `manuals`.* FROM `manuals` ","name":"Manual Load","connection_id":93140860,"binds":[]},"time":"2013-02-25T15:27:25+02:00","transaction_id":"aa656234c5e4dcb884c3","end":"2013-02-25T15:27:25+02:00","duration":12.87021},{"name":"sql.active_record","payload":{"sql":"SELECT `manuals`.* FROM `manuals`  WHERE `manuals`.`ochered` = 1","name":"Manual Load","connection_id":93140860,"binds":[]},"time":"2013-02-25T15:27:25+02:00","transaction_id":"aa656234c5e4dcb884c3","end":"2013-02-25T15:27:25+02:00","duration":0.375118},{"name":"sql.active_record","payload":{"sql":"SHOW FULL FIELDS FROM `types`","name":"SCHEMA","connection_id":93140860,"binds":[]},"time":"2013-02-25T15:27:25+02:00","transaction_id":"aa656234c5e4dcb884c3","end":"2013-02-25T15:27:25+02:00","duration":0.636045},{"name":"sql.active_record","payload":{"sql":"SELECT `types`.* FROM `types` ","name":"Type Load","connection_id":93140860,"binds":[]},"time":"2013-02-25T15:27:25+02:00","transaction_id":"aa656234c5e4dcb884c3","end":"2013-02-25T15:27:25+02:00","duration":0.979454},{"name":"sql.active_record","payload":{"sql":"SELECT `payments`.* FROM `payments`  WHERE `payments`.`type_id` = 1","name":"Payment Load","connection_id":93140860,"binds":[]},"time":"2013-02-25T15:27:26+02:00","transaction_id":"aa656234c5e4dcb884c3","end":"2013-02-25T15:27:26+02:00","duration":0.38580400000000004},{"name":"sql.active_record","payload":{"sql":"SELECT `manuals`.* FROM `manuals`  WHERE `manuals`.`payment_id` = 1","name":"Manual Load","connection_id":93140860,"binds":[]},"time":"2013-02-25T15:27:26+02:00","transaction_id":"aa656234c5e4dcb884c3","end":"2013-02-25T15:27:26+02:00","duration":1.182831},{"name":"sql.active_record","payload":{"sql":"SELECT `manuals`.* FROM `manuals`  WHERE `manuals`.`payment_id` = 2","name":"Manual Load","connection_id":93140860,"binds":[]},"time":"2013-02-25T15:27:26+02:00","transaction_id":"aa656234c5e4dcb884c3","end":"2013-02-25T15:27:26+02:00","duration":0.36527},{"name":"sql.active_record","payload":{"sql":"SELECT `payments`.* FROM `payments`  WHERE `payments`.`type_id` = 2","name":"Payment Load","connection_id":93140860,"binds":[]},"time":"2013-02-25T15:27:26+02:00","transaction_id":"aa656234c5e4dcb884c3","end":"2013-02-25T15:27:26+02:00","duration":0.35004399999999997},{"name":"sql.active_record","payload":{"sql":"SELECT `manuals`.* FROM `manuals`  WHERE `manuals`.`payment_id` = 3","name":"Manual Load","connection_id":93140860,"binds":[]},"time":"2013-02-25T15:27:26+02:00","transaction_id":"aa656234c5e4dcb884c3","end":"2013-02-25T15:27:26+02:00","duration":0.388947},{"name":"sql.active_record","payload":{"sql":"SELECT `manuals`.* FROM `manuals`  WHERE `manuals`.`payment_id` = 4","name":"Manual Load","connection_id":93140860,"binds":[]},"time":"2013-02-25T15:27:26+02:00","transaction_id":"aa656234c5e4dcb884c3","end":"2013-02-25T15:27:26+02:00","duration":0.334401},{"name":"sql.active_record","payload":{"sql":"SELECT `payments`.* FROM `payments`  WHERE `payments`.`type_id` = 3","name":"Payment Load","connection_id":93140860,"binds":[]},"time":"2013-02-25T15:27:26+02:00","transaction_id":"aa656234c5e4dcb884c3","end":"2013-02-25T15:27:26+02:00","duration":0.42337800000000003},{"name":"!render_template.action_view","payload":{"virtual_path":"payments/index"},"time":"2013-02-25T15:27:25+02:00","transaction_id":"1dd8cd49dbc9a7e308f3","end":"2013-02-25T15:27:26+02:00","duration":298.610113},{"name":"render_template.action_view","payload":{"identifier":"/home/taras/dev/project/rails/h/icn/app/views/payments/index.html.erb","layout":"layouts/application"},"time":"2013-02-25T15:27:25+02:00","transaction_id":"1dd8cd49dbc9a7e308f3","end":"2013-02-25T15:27:26+02:00","duration":298.643637},{"name":"!render_template.action_view","payload":{"virtual_path":"layouts/_header"},"time":"2013-02-25T15:27:26+02:00","transaction_id":"1dd8cd49dbc9a7e308f3","end":"2013-02-25T15:27:26+02:00","duration":1.8448589999999998},{"name":"render_partial.action_view","payload":{"identifier":"/home/taras/dev/project/rails/h/icn/app/views/layouts/_header.html.erb"},"time":"2013-02-25T15:27:26+02:00","transaction_id":"1dd8cd49dbc9a7e308f3","end":"2013-02-25T15:27:26+02:00","duration":1.892422},{"name":"!render_template.action_view","payload":{"virtual_path":"layouts/_footer"},"time":"2013-02-25T15:27:26+02:00","transaction_id":"1dd8cd49dbc9a7e308f3","end":"2013-02-25T15:27:26+02:00","duration":1.552643},{"name":"render_partial.action_view","payload":{"identifier":"/home/taras/dev/project/rails/h/icn/app/views/layouts/_footer.html.erb"},"time":"2013-02-25T15:27:26+02:00","transaction_id":"1dd8cd49dbc9a7e308f3","end":"2013-02-25T15:27:26+02:00","duration":1.60265},{"name":"!render_template.action_view","payload":{"virtual_path":"contact/_form"},"time":"2013-02-25T15:27:26+02:00","transaction_id":"1dd8cd49dbc9a7e308f3","end":"2013-02-25T15:27:26+02:00","duration":2.293098},{"name":"render_partial.action_view","payload":{"identifier":"/home/taras/dev/project/rails/h/icn/app/views/contact/_form.html.erb"},"time":"2013-02-25T15:27:26+02:00","transaction_id":"1dd8cd49dbc9a7e308f3","end":"2013-02-25T15:27:26+02:00","duration":2.3352120000000003},{"name":"!render_template.action_view","payload":{"virtual_path":"layouts/_popups"},"time":"2013-02-25T15:27:26+02:00","transaction_id":"1dd8cd49dbc9a7e308f3","end":"2013-02-25T15:27:26+02:00","duration":3.0347429999999997},{"name":"render_partial.action_view","payload":{"identifier":"/home/taras/dev/project/rails/h/icn/app/views/layouts/_popups.html.erb"},"time":"2013-02-25T15:27:26+02:00","transaction_id":"1dd8cd49dbc9a7e308f3","end":"2013-02-25T15:27:26+02:00","duration":3.068755},{"name":"!render_template.action_view","payload":{"virtual_path":"layouts/application"},"time":"2013-02-25T15:27:26+02:00","transaction_id":"1dd8cd49dbc9a7e308f3","end":"2013-02-25T15:27:26+02:00","duration":91.768722},{"name":"process_action.action_controller","payload":{"controller":"PaymentsController","action":"index","params":{"action":"index","controller":"payments"},"format":"html","method":"GET","path":"/payments","status":200,"view_runtime":410.142451,"db_runtime":56.280412000000005},"time":"2013-02-25T15:27:25+02:00","transaction_id":"1dd8cd49dbc9a7e308f3","end":"2013-02-25T15:27:26+02:00","duration":503.017881}]