[{"name":"start_processing.action_controller","payload":{"controller":"PaymentsController","action":"index","params":{"action":"index","controller":"payments"},"format":"html","method":"GET","path":"/payments"},"time":"2013-02-20T11:13:08+02:00","transaction_id":"2048a6c3b261a10a94f2","end":"2013-02-20T11:13:08+02:00","duration":0.00433},{"name":"sql.active_record","payload":{"sql":"SHOW FULL FIELDS FROM `payments`","name":"SCHEMA","connection_id":100301420,"binds":[]},"time":"2013-02-20T11:13:08+02:00","transaction_id":"b6afedb0ee8e85377467","end":"2013-02-20T11:13:08+02:00","duration":0.8039419999999999},{"name":"sql.active_record","payload":{"sql":"SHOW TABLES LIKE 'payments'","name":"SCHEMA","connection_id":100301420,"binds":[]},"time":"2013-02-20T11:13:08+02:00","transaction_id":"b6afedb0ee8e85377467","end":"2013-02-20T11:13:08+02:00","duration":0.344877},{"name":"sql.active_record","payload":{"sql":"SELECT `payments`.* FROM `payments` ","name":"Payment Load","connection_id":100301420,"binds":[]},"time":"2013-02-20T11:13:08+02:00","transaction_id":"b6afedb0ee8e85377467","end":"2013-02-20T11:13:08+02:00","duration":0.08164400000000001},{"name":"sql.active_record","payload":{"sql":"SHOW FULL FIELDS FROM `manuals`","name":"SCHEMA","connection_id":100301420,"binds":[]},"time":"2013-02-20T11:13:08+02:00","transaction_id":"b6afedb0ee8e85377467","end":"2013-02-20T11:13:08+02:00","duration":0.78725},{"name":"sql.active_record","payload":{"sql":"SHOW TABLES LIKE 'manuals'","name":"SCHEMA","connection_id":100301420,"binds":[]},"time":"2013-02-20T11:13:08+02:00","transaction_id":"b6afedb0ee8e85377467","end":"2013-02-20T11:13:08+02:00","duration":0.264209},{"name":"sql.active_record","payload":{"sql":"SELECT `manuals`.* FROM `manuals` ","name":"Manual Load","connection_id":100301420,"binds":[]},"time":"2013-02-20T11:13:08+02:00","transaction_id":"b6afedb0ee8e85377467","end":"2013-02-20T11:13:08+02:00","duration":0.090095},{"name":"sql.active_record","payload":{"sql":"SELECT `manuals`.* FROM `manuals`  WHERE `manuals`.`ochered` = 1","name":"Manual Load","connection_id":100301420,"binds":[]},"time":"2013-02-20T11:13:08+02:00","transaction_id":"b6afedb0ee8e85377467","end":"2013-02-20T11:13:08+02:00","duration":0.14967},{"name":"sql.active_record","payload":{"sql":"SHOW FULL FIELDS FROM `types`","name":"SCHEMA","connection_id":100301420,"binds":[]},"time":"2013-02-20T11:13:08+02:00","transaction_id":"b6afedb0ee8e85377467","end":"2013-02-20T11:13:08+02:00","duration":0.660558},{"name":"sql.active_record","payload":{"sql":"SHOW TABLES LIKE 'types'","name":"SCHEMA","connection_id":100301420,"binds":[]},"time":"2013-02-20T11:13:08+02:00","transaction_id":"b6afedb0ee8e85377467","end":"2013-02-20T11:13:08+02:00","duration":0.25212599999999996},{"name":"sql.active_record","payload":{"sql":"SELECT `types`.* FROM `types` ","name":"Type Load","connection_id":100301420,"binds":[]},"time":"2013-02-20T11:13:08+02:00","transaction_id":"b6afedb0ee8e85377467","end":"2013-02-20T11:13:08+02:00","duration":0.071657},{"name":"sql.active_record","payload":{"sql":"SELECT `payments`.* FROM `payments`  WHERE `payments`.`type_id` = 1","name":"Payment Load","connection_id":100301420,"binds":[]},"time":"2013-02-20T11:13:08+02:00","transaction_id":"b6afedb0ee8e85377467","end":"2013-02-20T11:13:08+02:00","duration":0.41381},{"name":"sql.active_record","payload":{"sql":"SELECT `manuals`.* FROM `manuals`  WHERE `manuals`.`payment_id` = 1","name":"Manual Load","connection_id":100301420,"binds":[]},"time":"2013-02-20T11:13:08+02:00","transaction_id":"b6afedb0ee8e85377467","end":"2013-02-20T11:13:08+02:00","duration":0.14492},{"name":"sql.active_record","payload":{"sql":"SELECT `manuals`.* FROM `manuals`  WHERE `manuals`.`payment_id` = 2","name":"Manual Load","connection_id":100301420,"binds":[]},"time":"2013-02-20T11:13:08+02:00","transaction_id":"b6afedb0ee8e85377467","end":"2013-02-20T11:13:08+02:00","duration":0.13248900000000002},{"name":"sql.active_record","payload":{"sql":"SELECT `payments`.* FROM `payments`  WHERE `payments`.`type_id` = 2","name":"Payment Load","connection_id":100301420,"binds":[]},"time":"2013-02-20T11:13:08+02:00","transaction_id":"b6afedb0ee8e85377467","end":"2013-02-20T11:13:08+02:00","duration":0.112514},{"name":"sql.active_record","payload":{"sql":"SELECT `manuals`.* FROM `manuals`  WHERE `manuals`.`payment_id` = 3","name":"Manual Load","connection_id":100301420,"binds":[]},"time":"2013-02-20T11:13:08+02:00","transaction_id":"b6afedb0ee8e85377467","end":"2013-02-20T11:13:08+02:00","duration":0.14101},{"name":"sql.active_record","payload":{"sql":"SELECT `manuals`.* FROM `manuals`  WHERE `manuals`.`payment_id` = 4","name":"Manual Load","connection_id":100301420,"binds":[]},"time":"2013-02-20T11:13:08+02:00","transaction_id":"b6afedb0ee8e85377467","end":"2013-02-20T11:13:08+02:00","duration":0.13772700000000002},{"name":"sql.active_record","payload":{"sql":"SELECT `payments`.* FROM `payments`  WHERE `payments`.`type_id` = 3","name":"Payment Load","connection_id":100301420,"binds":[]},"time":"2013-02-20T11:13:08+02:00","transaction_id":"b6afedb0ee8e85377467","end":"2013-02-20T11:13:08+02:00","duration":0.136401},{"name":"!render_template.action_view","payload":{"virtual_path":"payments/index"},"time":"2013-02-20T11:13:08+02:00","transaction_id":"2048a6c3b261a10a94f2","end":"2013-02-20T11:13:08+02:00","duration":206.167076},{"name":"render_template.action_view","payload":{"identifier":"/home/taras/dev/project/rails/h/icn/app/views/payments/index.html.erb","layout":"layouts/application"},"time":"2013-02-20T11:13:08+02:00","transaction_id":"2048a6c3b261a10a94f2","end":"2013-02-20T11:13:08+02:00","duration":206.19815499999999},{"name":"!render_template.action_view","payload":{"virtual_path":"layouts/_header"},"time":"2013-02-20T11:13:08+02:00","transaction_id":"2048a6c3b261a10a94f2","end":"2013-02-20T11:13:08+02:00","duration":1.9911759999999998},{"name":"render_partial.action_view","payload":{"identifier":"/home/taras/dev/project/rails/h/icn/app/views/layouts/_header.html.erb"},"time":"2013-02-20T11:13:08+02:00","transaction_id":"2048a6c3b261a10a94f2","end":"2013-02-20T11:13:08+02:00","duration":2.049984},{"name":"!render_template.action_view","payload":{"virtual_path":"layouts/_footer"},"time":"2013-02-20T11:13:08+02:00","transaction_id":"2048a6c3b261a10a94f2","end":"2013-02-20T11:13:08+02:00","duration":1.4514420000000001},{"name":"render_partial.action_view","payload":{"identifier":"/home/taras/dev/project/rails/h/icn/app/views/layouts/_footer.html.erb"},"time":"2013-02-20T11:13:08+02:00","transaction_id":"2048a6c3b261a10a94f2","end":"2013-02-20T11:13:08+02:00","duration":1.502148},{"name":"!render_template.action_view","payload":{"virtual_path":"layouts/_popups"},"time":"2013-02-20T11:13:08+02:00","transaction_id":"2048a6c3b261a10a94f2","end":"2013-02-20T11:13:08+02:00","duration":0.037435},{"name":"render_partial.action_view","payload":{"identifier":"/home/taras/dev/project/rails/h/icn/app/views/layouts/_popups.html.erb"},"time":"2013-02-20T11:13:08+02:00","transaction_id":"2048a6c3b261a10a94f2","end":"2013-02-20T11:13:08+02:00","duration":0.07025999999999999},{"name":"!render_template.action_view","payload":{"virtual_path":"layouts/application"},"time":"2013-02-20T11:13:08+02:00","transaction_id":"2048a6c3b261a10a94f2","end":"2013-02-20T11:13:08+02:00","duration":134.420517},{"name":"process_action.action_controller","payload":{"controller":"PaymentsController","action":"index","params":{"action":"index","controller":"payments"},"format":"html","method":"GET","path":"/payments","status":200,"view_runtime":369.09686700000003,"db_runtime":4.724899000000001},"time":"2013-02-20T11:13:08+02:00","transaction_id":"2048a6c3b261a10a94f2","end":"2013-02-20T11:13:08+02:00","duration":407.314998}]