[{"name":"start_processing.action_controller","payload":{"controller":"PagesController","action":"index","params":{"action":"index","controller":"pages"},"format":"html","method":"GET","path":"/pages"},"time":"2013-02-21T15:17:40+02:00","transaction_id":"82fe26f6468933e76bac","end":"2013-02-21T15:17:40+02:00","duration":0.004679},{"name":"sql.active_record","payload":{"sql":"SELECT `pages`.* FROM `pages`  WHERE (start_at < '2013-02-21 13:17:40' ) AND (finish_at > '2013-02-21 13:17:40' )","name":"Page Load","connection_id":94802920,"binds":[]},"time":"2013-02-21T15:17:40+02:00","transaction_id":"3ba707244727ce92eba0","end":"2013-02-21T15:17:40+02:00","duration":0.381124},{"name":"sql.active_record","payload":{"sql":"SELECT  `posts`.* FROM `posts`  WHERE `posts`.`post_type_id` = 1 ORDER BY `posts`.`id` DESC LIMIT 1","name":"Post Load","connection_id":94802920,"binds":[]},"time":"2013-02-21T15:17:40+02:00","transaction_id":"3ba707244727ce92eba0","end":"2013-02-21T15:17:40+02:00","duration":0.116914},{"name":"sql.active_record","payload":{"sql":"SELECT  `posts`.* FROM `posts`  WHERE `posts`.`post_type_id` = 2 ORDER BY `posts`.`id` DESC LIMIT 1","name":"Post Load","connection_id":94802920,"binds":[]},"time":"2013-02-21T15:17:40+02:00","transaction_id":"3ba707244727ce92eba0","end":"2013-02-21T15:17:40+02:00","duration":0.091771},{"name":"sql.active_record","payload":{"sql":"SELECT  `abouts`.* FROM `abouts`  ORDER BY `abouts`.`id` DESC LIMIT 1","name":"About Load","connection_id":94802920,"binds":[]},"time":"2013-02-21T15:17:40+02:00","transaction_id":"3ba707244727ce92eba0","end":"2013-02-21T15:17:40+02:00","duration":0.103505},{"name":"!render_template.action_view","payload":{"virtual_path":"pages/index"},"time":"2013-02-21T15:17:40+02:00","transaction_id":"82fe26f6468933e76bac","end":"2013-02-21T15:17:40+02:00","duration":5.663360999999999},{"name":"render_template.action_view","payload":{"identifier":"/home/taras/dev/project/rails/h/icn/app/views/pages/index.html.erb","layout":"layouts/application"},"time":"2013-02-21T15:17:40+02:00","transaction_id":"82fe26f6468933e76bac","end":"2013-02-21T15:17:40+02:00","duration":5.710014999999999},{"name":"!render_template.action_view","payload":{"virtual_path":"layouts/_header"},"time":"2013-02-21T15:17:40+02:00","transaction_id":"82fe26f6468933e76bac","end":"2013-02-21T15:17:40+02:00","duration":1.9056190000000002},{"name":"render_partial.action_view","payload":{"identifier":"/home/taras/dev/project/rails/h/icn/app/views/layouts/_header.html.erb"},"time":"2013-02-21T15:17:40+02:00","transaction_id":"82fe26f6468933e76bac","end":"2013-02-21T15:17:40+02:00","duration":1.9825149999999998},{"name":"!render_template.action_view","payload":{"virtual_path":"layouts/_footer"},"time":"2013-02-21T15:17:40+02:00","transaction_id":"82fe26f6468933e76bac","end":"2013-02-21T15:17:40+02:00","duration":1.336902},{"name":"render_partial.action_view","payload":{"identifier":"/home/taras/dev/project/rails/h/icn/app/views/layouts/_footer.html.erb"},"time":"2013-02-21T15:17:40+02:00","transaction_id":"82fe26f6468933e76bac","end":"2013-02-21T15:17:40+02:00","duration":1.384533},{"name":"!render_template.action_view","payload":{"virtual_path":"contact/_form"},"time":"2013-02-21T15:17:40+02:00","transaction_id":"82fe26f6468933e76bac","end":"2013-02-21T15:17:40+02:00","duration":6.054265},{"name":"render_partial.action_view","payload":{"identifier":"/home/taras/dev/project/rails/h/icn/app/views/contact/_form.html.erb"},"time":"2013-02-21T15:17:40+02:00","transaction_id":"82fe26f6468933e76bac","end":"2013-02-21T15:17:40+02:00","duration":6.102804},{"name":"!render_template.action_view","payload":{"virtual_path":"layouts/_popups"},"time":"2013-02-21T15:17:40+02:00","transaction_id":"82fe26f6468933e76bac","end":"2013-02-21T15:17:40+02:00","duration":6.788925000000001},{"name":"render_partial.action_view","payload":{"identifier":"/home/taras/dev/project/rails/h/icn/app/views/layouts/_popups.html.erb"},"time":"2013-02-21T15:17:40+02:00","transaction_id":"82fe26f6468933e76bac","end":"2013-02-21T15:17:40+02:00","duration":6.82196},{"name":"!render_template.action_view","payload":{"virtual_path":"layouts/application"},"time":"2013-02-21T15:17:40+02:00","transaction_id":"82fe26f6468933e76bac","end":"2013-02-21T15:17:40+02:00","duration":171.580409},{"name":"process_action.action_controller","payload":{"controller":"PagesController","action":"index","params":{"action":"index","controller":"pages"},"format":"html","method":"GET","path":"/pages","status":200,"view_runtime":182.55275400000002,"db_runtime":0.693314},"time":"2013-02-21T15:17:40+02:00","transaction_id":"82fe26f6468933e76bac","end":"2013-02-21T15:17:40+02:00","duration":187.36586499999999}]